AUTHORS.md
LICENSE
README.md
esteid/__init__.py
esteid/actions.py
esteid/authentication/README.md
esteid/authentication/__init__.py
esteid/authentication/authenticator.py
esteid/authentication/types.py
esteid/authentication/views.py
esteid/base_service.py
esteid/compat.py
esteid/constants.py
esteid/context_processors.py
esteid/exceptions.py
esteid/flowtest/README.md
esteid/flowtest/__init__.py
esteid/flowtest/signer.py
esteid/flowtest/urls.py
esteid/flowtest/views.py
esteid/generic.py
esteid/idcard/README.md
esteid/idcard/__init__.py
esteid/idcard/authenticator.py
esteid/idcard/signer.py
esteid/idcard/types.py
esteid/locale/en/LC_MESSAGES/django.mo
esteid/locale/en/LC_MESSAGES/django.po
esteid/locale/et/LC_MESSAGES/django.mo
esteid/locale/et/LC_MESSAGES/django.po
esteid/locale/lt/LC_MESSAGES/django.mo
esteid/locale/lt/LC_MESSAGES/django.po
esteid/locale/ru/LC_MESSAGES/django.mo
esteid/locale/ru/LC_MESSAGES/django.po
esteid/mixins.py
esteid/mobileid/README.md
esteid/mobileid/__init__.py
esteid/mobileid/authenticator.py
esteid/mobileid/base.py
esteid/mobileid/constants.py
esteid/mobileid/i18n.py
esteid/mobileid/signer.py
esteid/mobileid/types.py
esteid/mobileid/utils.py
esteid/ocsp.py
esteid/session.py
esteid/settings.py
esteid/signing/README.md
esteid/signing/__init__.py
esteid/signing/signer.py
esteid/signing/types.py
esteid/signing/views.py
esteid/smartid/README.md
esteid/smartid/__init__.py
esteid/smartid/apps.py
esteid/smartid/authenticator.py
esteid/smartid/base.py
esteid/smartid/constants.py
esteid/smartid/i18n.py
esteid/smartid/signer.py
esteid/smartid/types.py
esteid/smartid/utils.py
esteid/static/esteid-helper/Esteid.main.web.js
esteid/static/esteid-helper/Esteid.main.web.min.js
esteid/static/esteid-helper/web-eid.js
esteid/static/images/esteid/id-kaart-btn.png
esteid/static/images/esteid/mid-btn.png
esteid/static/images/esteid/smart-id-btn.png
esteid/static/images/esteid/smartID-logo-btn.png
esteid/templates/esteid/auth-new.html
django_esteid-4.2.dist-info/LICENSE
django_esteid-4.2.dist-info/METADATA
django_esteid-4.2.dist-info/WHEEL
django_esteid-4.2.dist-info/RECORD
