Metadata-Version: 2.1
Name: django-esteid
Version: 4.2
Summary: Django-esteid is a package that provides Esteid based authentication for your Django applications.
Home-page: https://github.com/thorgate/django-esteid
License: BSD
Keywords: esteid,django,smartid,mobile-id,idcard,asice
Author: Thorgate
Author-email: info@thorgate.eu
Maintainer: Jyrno Ader
Maintainer-email: jyrno42@gmail.com
Requires-Python: >=3.8.0,<4.0.0
Classifier: Development Status :: 5 - Production/Stable
Classifier: Framework :: Django
Classifier: Intended Audience :: Developers
Classifier: License :: OSI Approved :: BSD License
Classifier: License :: Other/Proprietary License
Classifier: Natural Language :: English
Classifier: Programming Language :: Python :: 3
Classifier: Programming Language :: Python :: 3.8
Classifier: Programming Language :: Python :: 3.9
Classifier: Programming Language :: Python :: 3.10
Classifier: Programming Language :: Python :: 3.11
Classifier: Programming Language :: Python :: 3
Classifier: Programming Language :: Python :: 3.6
Classifier: Programming Language :: Python :: 3.7
Classifier: Programming Language :: Python :: 3.8
Classifier: Programming Language :: Python :: 3.9
Requires-Dist: Django (>=1.11,!=2.1.0,!=2.1.1)
Requires-Dist: attrs (>=19.2.0)
Requires-Dist: backports.zoneinfo (==0.2.1) ; python_version < "3.9"
Requires-Dist: esteid-certificates (>=1.0.0,<1.1.0)
Requires-Dist: pyasice (>=1.2.0)
Requires-Dist: pytz (>=2018)
Requires-Dist: requests (>=2.20)
Project-URL: Repository, https://github.com/thorgate/django-esteid
